pydantic_cache/__init__.py
pydantic_cache/backend/__init__.py
pydantic_cache/backend/base.py
pydantic_cache/backend/disk.py
pydantic_cache/backend/redis.py
pydantic_cache/decorator.py
pydantic_cache/py.typed
pydantic_cache-0.1.0.dist-info/LICENSE.txt
pydantic_cache-0.1.0.dist-info/METADATA
pydantic_cache-0.1.0.dist-info/WHEEL
pydantic_cache-0.1.0.dist-info/RECORD
