Metadata-Version: 2.1
Name: pydantic-cache
Version: 0.1.0
Summary: 
Home-page: https://github.com/jacksmith15/pydantic-cache
Author: Jack Smith
Requires-Python: >=3.10,<4.0
Classifier: Programming Language :: Python :: 3
Classifier: Programming Language :: Python :: 3.10
Classifier: Programming Language :: Python :: 3.11
Provides-Extra: redis
Requires-Dist: pydantic (>=2.6.1,<3.0.0)
Requires-Dist: redis (>=5.0.1,<6.0.0) ; extra == "redis"
Project-URL: Repository, https://github.com/jacksmith15/pydantic-cache
